{
  "geometry":[
    {
      "type":"sphere",
      "centre":[0, 0, -2],
      "radius":0.8,

      "ac":[1,1,1],
      "dc":[0.85,0.85,0.29],
      "sc":[0.3,0.3,0.3],

      "ka":0,
      "kd":1,
      "ks":1,

      "pc":10
    },
    {
      "type":"sphere",
      "centre":[1.2, 0, -2],
      "radius":0.3,

      "ac":[1,1,1],
      "dc":[0.16,0.40,0.54],
      "sc":[0,0,0],

      "ka":0,
      "kd":1,
      "ks":0,

      "pc":0
    },
    {
      "type":"sphere",
      "centre":[-1.2, 0, -2],
      "radius":0.3,

      "ac":[1,1,1],
      "dc":[0.16,0.40,0.54],
      "sc":[0,0,0],

      "ka":0,
      "kd":1,
      "ks":0,

      "pc":0
    },
    {
      "type":"sphere",
      "centre":[0, 0, -0.8],
      "radius":0.3,

      "ac":[1,1,1],
      "dc":[0.16,0.40,0.54],
      "sc":[0,0,0],

      "ka":0,
      "kd":1,
      "ks":0,

      "pc":0
    },
    {
      "type":"sphere",
      "centre":[0, 0, -3.2],
      "radius":0.3,

      "ac":[1,1,1],
      "dc":[0.16,0.40,0.54],
      "sc":[0,0,0],

      "ka":0,
      "kd":1,
      "ks":0,

      "pc":0
    },
    {
      "type":"sphere",
      "centre":[1, 0, -0.6],
      "radius":0.15,

      "ac":[1,1,1],
      "dc":[0.45,0.11,0.89],
      "sc":[0,0,0],

      "ka":0,
      "kd":1,
      "ks":0,

      "pc":0
    },
    {
      "type":"sphere",
      "centre":[1, 0, -3],
      "radius":0.15,

      "ac":[1,1,1],
      "dc":[0.45,0.11,0.89],
      "sc":[0,0,0],

      "ka":0,
      "kd":1,
      "ks":0,

      "pc":0
    },
    {
      "type":"sphere",
      "centre":[-1, 0, -0.6],
      "radius":0.15,

      "ac":[1,1,1],
      "dc":[0.45,0.11,0.89],
      "sc":[0,0,0],

      "ka":0,
      "kd":1,
      "ks":0,

      "pc":0
    },
    {
      "type":"sphere",
      "centre":[-1, 0, -3],
      "radius":0.15,

      "ac":[1,1,1],
      "dc":[0.45,0.11,0.89],
      "sc":[0,0,0],

      "ka":0,
      "kd":1,
      "ks":0,

      "pc":0
    },
    {
      "type":"rectangle",
      "p1":[-2.5, 4, -4],
      "p2":[-2.5, -2, -4],
      "p3":[4.5, -2, -4],
      "p4":[4.5, 4, -4],

      "ac":[1,1,1],
      "dc":[1,1,1],
      "sc":[0,0,0],

      "ka":0,
      "kd":1,
      "ks":0,

      "pc":0
    },
    {
      "type":"rectangle",
      "p1":[-2.5, -2, -4],
      "p2":[-2.5, -2, 0],
      "p3":[4.5, -2, 0],
      "p4":[4.5, -2, -4],

      "ac":[1,1,1],
      "dc":[1,1,1],
      "sc":[0,0,0],

      "ka":0,
      "kd":0.5,
      "ks":0,

      "pc":0
    },
    {
      "type":"rectangle",
      "p1":[4.5, -2, -4],
      "p2":[4.5, -2, 0],
      "p3":[4.5, 4, 0],
      "p4":[4.5, 4, -4],

      "ac":[1,1,1],
      "dc":[1,1,1],
      "sc":[0,0,0],

      "ka":0,
      "kd":1,
      "ks":0,

      "pc":0
    }
  ],
  "light":[
    {
      "type":"area",
      "p1":[-8, 5, -4],
      "p2":[-8, 5, -2],
      "p3":[2, 8, -2],
      "p4":[2, 8, -4],

      "id":[1, 1, 1],
      "is":[1, 1, 1],

      "n": 5,
      "usecenter": true
    }
  ],
  "output":[
    {
      "filename":"40120317_local.ppm",
      "size":[500,375],
      "lookat":[1,-1,-1],
      "up":[0,1,0],
      "fov":60,
      "centre":[-4, 3, 1],
      "ai":[1,1,1],
      "bkc":[0.5,0.5,0.5]
    },
    {
      "filename":"40120317_global.ppm",
      "size":[500,375],
      "lookat":[1,-1,-1],
      "up":[0,1,0],
      "fov":60,
      "centre":[-4, 3, 1],
      "ai":[1,1,1],
      "bkc":[0.5,0.5,0.5],

      "globalillum": true,
      "raysperpixel": [1],
      "maxbounces": 3,
      "probterminate": 0.333
    }
  ]
}
